{
  "id": "3b9028cf-20d2-4bce-8d54-6817122660e6",
  "prevId": "00000000-0000-0000-0000-000000000000",
  "version": "7",
  "dialect": "postgresql",
  "tables": {
    "public.goals": {
      "name": "goals",
      "schema": "",
      "columns": {
        "id": {
          "name": "id",
          "type": "text",
          "primaryKey": true,
          "notNull": true
        },
        "board_id": {
          "name": "board_id",
          "type": "text",
          "primaryKey": false,
          "notNull": true
        },
        "title": {
          "name": "title",
          "type": "text",
          "primaryKey": false,
          "notNull": true
        },
        "generated_image_url": {
          "name": "generated_image_url",
          "type": "text",
          "primaryKey": false,
          "notNull": false
        },
        "phrase": {
          "name": "phrase",
          "type": "text",
          "primaryKey": false,
          "notNull": false
        },
        "position_x": {
          "name": "position_x",
          "type": "integer",
          "primaryKey": false,
          "notNull": true,
          "default": 0
        },
        "position_y": {
          "name": "position_y",
          "type": "integer",
          "primaryKey": false,
          "notNull": true,
          "default": 0
        },
        "width": {
          "name": "width",
          "type": "integer",
          "primaryKey": false,
          "notNull": true,
          "default": 300
        },
        "height": {
          "name": "height",
          "type": "integer",
          "primaryKey": false,
          "notNull": true,
          "default": 300
        },
        "created_at": {
          "name": "created_at",
          "type": "timestamp",
          "primaryKey": false,
          "notNull": true,
          "default": "now()"
        }
      },
      "indexes": {},
      "foreignKeys": {
        "goals_board_id_vision_boards_id_fk": {
          "name": "goals_board_id_vision_boards_id_fk",
          "tableFrom": "goals",
          "tableTo": "vision_boards",
          "columnsFrom": ["board_id"],
          "columnsTo": ["id"],
          "onDelete": "cascade",
          "onUpdate": "no action"
        }
      },
      "compositePrimaryKeys": {},
      "uniqueConstraints": {},
      "policies": {},
      "checkConstraints": {},
      "isRLSEnabled": false
    },
    "public.purchases": {
      "name": "purchases",
      "schema": "",
      "columns": {
        "id": {
          "name": "id",
          "type": "text",
          "primaryKey": true,
          "notNull": true
        },
        "user_id": {
          "name": "user_id",
          "type": "text",
          "primaryKey": false,
          "notNull": true
        },
        "polar_order_id": {
          "name": "polar_order_id",
          "type": "text",
          "primaryKey": false,
          "notNull": true
        },
        "amount": {
          "name": "amount",
          "type": "integer",
          "primaryKey": false,
          "notNull": true
        },
        "credits_added": {
          "name": "credits_added",
          "type": "integer",
          "primaryKey": false,
          "notNull": true
        },
        "created_at": {
          "name": "created_at",
          "type": "timestamp",
          "primaryKey": false,
          "notNull": true,
          "default": "now()"
        }
      },
      "indexes": {},
      "foreignKeys": {},
      "compositePrimaryKeys": {},
      "uniqueConstraints": {
        "purchases_polar_order_id_unique": {
          "name": "purchases_polar_order_id_unique",
          "nullsNotDistinct": false,
          "columns": ["polar_order_id"]
        }
      },
      "policies": {},
      "checkConstraints": {},
      "isRLSEnabled": false
    },
    "public.user_credits": {
      "name": "user_credits",
      "schema": "",
      "columns": {
        "user_id": {
          "name": "user_id",
          "type": "text",
          "primaryKey": true,
          "notNull": true
        },
        "image_credits": {
          "name": "image_credits",
          "type": "integer",
          "primaryKey": false,
          "notNull": true,
          "default": 0
        },
        "total_purchased": {
          "name": "total_purchased",
          "type": "integer",
          "primaryKey": false,
          "notNull": true,
          "default": 0
        },
        "polar_customer_id": {
          "name": "polar_customer_id",
          "type": "text",
          "primaryKey": false,
          "notNull": false
        },
        "updated_at": {
          "name": "updated_at",
          "type": "timestamp",
          "primaryKey": false,
          "notNull": true,
          "default": "now()"
        }
      },
      "indexes": {},
      "foreignKeys": {},
      "compositePrimaryKeys": {},
      "uniqueConstraints": {},
      "policies": {},
      "checkConstraints": {},
      "isRLSEnabled": false
    },
    "public.vision_boards": {
      "name": "vision_boards",
      "schema": "",
      "columns": {
        "id": {
          "name": "id",
          "type": "text",
          "primaryKey": true,
          "notNull": true
        },
        "visitor_id": {
          "name": "visitor_id",
          "type": "text",
          "primaryKey": false,
          "notNull": false
        },
        "user_id": {
          "name": "user_id",
          "type": "text",
          "primaryKey": false,
          "notNull": false
        },
        "user_photo_url": {
          "name": "user_photo_url",
          "type": "text",
          "primaryKey": false,
          "notNull": true
        },
        "user_photo_no_bg_url": {
          "name": "user_photo_no_bg_url",
          "type": "text",
          "primaryKey": false,
          "notNull": true
        },
        "created_at": {
          "name": "created_at",
          "type": "timestamp",
          "primaryKey": false,
          "notNull": true,
          "default": "now()"
        }
      },
      "indexes": {},
      "foreignKeys": {},
      "compositePrimaryKeys": {},
      "uniqueConstraints": {},
      "policies": {},
      "checkConstraints": {},
      "isRLSEnabled": false
    }
  },
  "enums": {},
  "schemas": {},
  "sequences": {},
  "roles": {},
  "policies": {},
  "views": {},
  "_meta": {
    "columns": {},
    "schemas": {},
    "tables": {}
  }
}
